widpath/__init__.py
widpath/resolver.py
widpath-0.1.1.dist-info/licenses/LICENSE
widpath-0.1.1.dist-info/METADATA
widpath-0.1.1.dist-info/WHEEL
widpath-0.1.1.dist-info/top_level.txt
widpath-0.1.1.dist-info/RECORD
