Metadata-Version: 2.4
Name: widpath
Version: 0.1.1
Summary: A hierarchical file path resolver for WID-based storage
Author-email: "sheng.SMLH" <sheng@smlh.com>
Project-URL: Homepage, https://github.com/yourusername/widpath
Keywords: wid,file storage,hierarchical path
Requires-Python: >=3.8
License-File: LICENSE
Dynamic: license-file
